odoo/addons/l10n_be_cooperator_national_number/README.rst
odoo/addons/l10n_be_cooperator_national_number/__init__.py
odoo/addons/l10n_be_cooperator_national_number/__manifest__.py
odoo/addons/l10n_be_cooperator_national_number/i18n/it.po
odoo/addons/l10n_be_cooperator_national_number/i18n/l10n_be_cooperator_national_number.pot
odoo/addons/l10n_be_cooperator_national_number/models/__init__.py
odoo/addons/l10n_be_cooperator_national_number/models/res_company.py
odoo/addons/l10n_be_cooperator_national_number/models/res_config_settings.py
odoo/addons/l10n_be_cooperator_national_number/models/res_partner.py
odoo/addons/l10n_be_cooperator_national_number/models/subscription_request.py
odoo/addons/l10n_be_cooperator_national_number/readme/CONTRIBUTORS.rst
odoo/addons/l10n_be_cooperator_national_number/readme/DESCRIPTION.rst
odoo/addons/l10n_be_cooperator_national_number/readme/HISTORY.rst
odoo/addons/l10n_be_cooperator_national_number/readme/USAGE.rst
odoo/addons/l10n_be_cooperator_national_number/static/description/icon.png
odoo/addons/l10n_be_cooperator_national_number/static/description/index.html
odoo/addons/l10n_be_cooperator_national_number/tests/__init__.py
odoo/addons/l10n_be_cooperator_national_number/tests/test_cooperator_national_number.py
odoo/addons/l10n_be_cooperator_national_number/views/res_config_settings.xml
odoo/addons/l10n_be_cooperator_national_number/views/subscription_request_view.xml
odoo_addon_l10n_be_cooperator_national_number-16.0.2.1.1.2.dist-info/METADATA
odoo_addon_l10n_be_cooperator_national_number-16.0.2.1.1.2.dist-info/WHEEL
odoo_addon_l10n_be_cooperator_national_number-16.0.2.1.1.2.dist-info/top_level.txt
odoo_addon_l10n_be_cooperator_national_number-16.0.2.1.1.2.dist-info/RECORD
